cluster_setup/__about__.py
cluster_setup/__init__.py
cluster_setup/__main__.py
cluster_setup/cli.py
cluster_setup/config.py
cluster_setup/git.py
cluster_setup/install.py
cluster_setup/main.py
cluster_setup/options.py
cluster_setup/py.typed
cluster_setup/templating.py
cluster_setup/test.py
cluster_setup/unpack.py
cluster_setup/venv.py
cluster_setup/tests/conftest.py
cluster_setup/tests/test_cli.py
cluster_setup/tests/test_config.py
cluster_setup/tests/test_git.py
cluster_setup/tests/test_install.py
cluster_setup/tests/test_options.py
cluster_setup/tests/test_templating.py
cluster_setup/tests/test_venv.py
cluster_setup-0.0.1.dist-info/METADATA
cluster_setup-0.0.1.dist-info/WHEEL
cluster_setup-0.0.1.dist-info/entry_points.txt
cluster_setup-0.0.1.dist-info/licenses/LICENSE
cluster_setup-0.0.1.dist-info/RECORD
