Metadata-Version: 2.4
Name: cluster-setup
Version: 0.0.1
Summary: Set up a remote cluster for computational chemistry
Project-URL: Documentation, https://github.com/ugognw/cluster-setup#readme
Project-URL: Issues, https://github.com/ugognw/cluster-setup/issues
Project-URL: Source, https://github.com/ugognw/cluster-setup
Author-email: Ugochukwu Nwosu <ugognw@gmail.com>
License-Expression: MIT
License-File: LICENSE
Classifier: Development Status :: 4 - Beta
Classifier: Programming Language :: Python
Classifier: Programming Language :: Python :: 3.10
Classifier: Programming Language :: Python :: 3.11
Classifier: Programming Language :: Python :: 3.12
Classifier: Programming Language :: Python :: 3.13
Classifier: Programming Language :: Python :: 3.14
Classifier: Programming Language :: Python :: Implementation :: CPython
Requires-Python: >=3.10
Requires-Dist: jinja2>=3.1.6
Requires-Dist: tomli>=1.1.0; python_version < '3.11'
Provides-Extra: dev
Requires-Dist: bump-my-version>=1.2.0; extra == 'dev'
Requires-Dist: mypy>=1.17.0; extra == 'dev'
Requires-Dist: pre-commit>=2.20.0; extra == 'dev'
Requires-Dist: ruff>=0.12.3; extra == 'dev'
Provides-Extra: test
Requires-Dist: pytest-cov>=6.0.0; extra == 'test'
Requires-Dist: pytest-datadir>=1.7.2; extra == 'test'
Requires-Dist: pytest-xdist>=3.8.0; extra == 'test'
Requires-Dist: pytest>=8.4.1; extra == 'test'
